nowhatstream/__init__.py
nowhatstream/apivideo_request.py
nowhatstream/stream.py
nowhatstream/video.py
nowhatstream/build/__init__.py
nowhatstream/build/lib/__init__.py
nowhatstream/build/lib/nowhatstream/__init__.py
nowhatstream/build/lib/nowhatstream/apivideo_request.py
nowhatstream/build/lib/nowhatstream/stream.py
nowhatstream/config/__init__.py
nowhatstream/config/streamcomfiguration.py
nowhatstream-0.0.9.dist-info/LICENSE
nowhatstream-0.0.9.dist-info/METADATA
nowhatstream-0.0.9.dist-info/WHEEL
nowhatstream-0.0.9.dist-info/top_level.txt
nowhatstream-0.0.9.dist-info/RECORD
