Metadata-Version: 2.1
Name: nowhatstream
Version: 0.0.9
Summary: The interface between apivideo and us
Home-page: https://gitlab.com/NOWhatech/nowhat-stream.git
Author: Louis Lesueur
Author-email: louis.l@nowhat.fr
License: UNKNOWN
Platform: UNKNOWN
Classifier: Programming Language :: Python :: 3
Classifier: License :: OSI Approved :: MIT License
Classifier: Operating System :: OS Independent
